perma/__init__.py
perma/apps.py
perma/blocks.py
perma/default_settings.py
perma/html_to_text.py
perma/model_fields.py
perma/model_porter.py
perma/models.py
perma/side_panels.py
perma/utilities.py
perma/views.py
perma/wagtail_hooks.py
perma/wagtail_settings.py
perma/migrations/0001_initial.py
perma/migrations/__init__.py
perma/templates/perma/base_page.html
perma/templates/perma/record.html
perma/templates/perma/record_index_page.html
perma/templates/perma/record_page.html
perma/templates/perma/blocks/binary_file_block.html
perma/templates/perma/blocks/csv_file_block.html
perma/templates/perma/blocks/excel_file_block.html
perma/templates/perma/blocks/file_block.html
perma/templates/perma/blocks/json_file_block.html
perma/templates/perma/blocks/record_authors_block.html
perma/templates/perma/blocks/record_block.html
perma/templates/perma/blocks/record_dates_block.html
perma/templates/perma/blocks/record_description_block.html
perma/templates/perma/blocks/record_requirements_block.html
perma/templates/perma/blocks/record_resources_block.html
perma/templates/perma/blocks/record_tags_block.html
perma/templates/perma/blocks/requirement_block.html
perma/templates/perma/blocks/software_requirement_block.html
perma/templates/perma/blocks/text_file_block.html
perma/templates/perma/blocks/xml_file_block.html
perma/templates/perma/tags/support.html
perma/templatetags/__init__.py
perma/templatetags/perma_tags.py
perma-4.1.0.dist-info/AUTHORS.txt
perma-4.1.0.dist-info/LICENSE.txt
perma-4.1.0.dist-info/METADATA
perma-4.1.0.dist-info/WHEEL
perma-4.1.0.dist-info/top_level.txt
perma-4.1.0.dist-info/zip-safe
perma-4.1.0.dist-info/RECORD
