Metadata-Version: 2.1
Name: perma
Version: 4.1.0
Summary: A Wagtail app for keeping records under a unique, permanent URL.
Home-page: https://github.com/high-dimensional/perma
Author: High Dimensional Neurology Group, UCL
Author-email: pypi@highdimensional.net
License: BSD-3-Clause
Platform: any
Classifier: Framework :: Django
Classifier: Framework :: Wagtail
Classifier: Programming Language :: Python :: 3
Classifier: Programming Language :: Python :: 3.8
Classifier: License :: OSI Approved :: BSD License
Classifier: Operating System :: OS Independent
Requires-Python: >=3.8
License-File: LICENSE.txt
License-File: AUTHORS.txt
Requires-Dist: Django (<4.2,>=4.1)
Requires-Dist: wagtail (<4.2,>=4.1)
Requires-Dist: beautifulsoup4 (<4.12,>=4.11)
Requires-Dist: django-auxiliaries (<4.2,>=4.1)
Requires-Dist: js-initiator (<4.2,>=4.1)
Requires-Dist: adede (<4.2,>=4.1)
Requires-Dist: morsels (<4.2,>=4.1)
Requires-Dist: model-porter (<4.2,>=4.1)
Requires-Dist: wagtail-switch-block (<4.2,>=4.1)
Requires-Dist: wagtail-tags-block (<4.2,>=4.1)
Requires-Dist: tour-guide (<4.2,>=4.1)
Requires-Dist: media-catalogue (<4.2,>=4.1.2)
Requires-Dist: figurative (<4.2,>=4.1)
Requires-Dist: wagtail-synopsis (<4.2,>=4.1)
Requires-Dist: officekit (<4.2,>=4.1)
